poc_poetry_partifact_plugin/__init__.py
poc_poetry_partifact_plugin/plugin.py
poc_poetry_partifact_plugin-0.18.0.dist-info/LICENSE
poc_poetry_partifact_plugin-0.18.0.dist-info/METADATA
poc_poetry_partifact_plugin-0.18.0.dist-info/WHEEL
poc_poetry_partifact_plugin-0.18.0.dist-info/entry_points.txt
poc_poetry_partifact_plugin-0.18.0.dist-info/RECORD
